micro.py
omg.py
omg.py-0.3.3.dist-info/LICENSE
omg.py-0.3.3.dist-info/METADATA
omg.py-0.3.3.dist-info/WHEEL
omg.py-0.3.3.dist-info/top_level.txt
omg.py-0.3.3.dist-info/RECORD
