Metadata-Version: 2.1
Name: omg.py
Version: 0.3.3
Summary: A micro-framework for the OMG, and code written in Python 3.6+.
Home-page: https://github.com/microservices/omg.py
Author: Asyncy
Author-email: me@kennethreitz.org
License: MIT
Platform: UNKNOWN
Classifier: License :: OSI Approved :: MIT License
Classifier: Programming Language :: Python
Classifier: Programming Language :: Python :: 3
Classifier: Programming Language :: Python :: 3.6
Classifier: Programming Language :: Python :: 3.7
Classifier: Programming Language :: Python :: Implementation :: CPython
Classifier: Programming Language :: Python :: Implementation :: PyPy
Requires-Python: >=3.6.0
Requires-Dist: pyyaml
Requires-Dist: Flask
Requires-Dist: waitress
Requires-Dist: setproctitle
